pyqt_files_already_exists_dialog/__init__.py
pyqt_files_already_exists_dialog/existsFileListWidget.py
pyqt_files_already_exists_dialog/filesAlreadyExistDialog.py
pyqt_files_already_exists_dialog-0.0.1.dist-info/LICENSE
pyqt_files_already_exists_dialog-0.0.1.dist-info/METADATA
pyqt_files_already_exists_dialog-0.0.1.dist-info/WHEEL
pyqt_files_already_exists_dialog-0.0.1.dist-info/top_level.txt
pyqt_files_already_exists_dialog-0.0.1.dist-info/RECORD
