Metadata-Version: 2.1
Name: pyqt-files-already-exists-dialog
Version: 0.0.1
Summary: PyQt files already exists dialog. Like "These files already exist, Would you add files except for these? (Yes/No)"
Home-page: https://github.com/yjg30737/pyqt-files-already-exists-dialog.git
Author: Jung Gyu Yoon
Author-email: yjg30737@gmail.com
License: MIT
Platform: UNKNOWN
License-File: LICENSE
Requires-Dist: PyQt5 (>=5.8)
Requires-Dist: simplePyQt5 (>=0.0.1)
